README.md
setup.cfg
setup.py
silabel/__init__.py
silabel/_fonologi.py
silabel/sample.py
silabel/silabel.py
silabel.egg-info/PKG-INFO
silabel.egg-info/SOURCES.txt
silabel.egg-info/dependency_links.txt
silabel.egg-info/requires.txt
silabel.egg-info/top_level.txt