Metadata-Version: 2.1
Name: silabel
Version: 0.4
Summary: Silabel is a python package to syllabelize indonesian word
Home-page: https://github.com/WiraDKP/indonesian_syllabelizer
Author: Wira Dharma Kencana Putra
Author-email: wiradharma_kencanaputra@yahoo.com
License: UNKNOWN
Keywords: silabel syllable indonesian indonesia jcop nlp bahasa
Platform: UNKNOWN
Classifier: Programming Language :: Python :: 3.7
Classifier: Intended Audience :: Developers
Classifier: Intended Audience :: Education
Classifier: Intended Audience :: Information Technology
Classifier: Intended Audience :: Science/Research
Classifier: Topic :: Scientific/Engineering :: Artificial Intelligence
Classifier: Natural Language :: Indonesian
Requires-Python: >=3.6
